[
	{
		"id": 1,
		"shirtNumber": 22,
		"givenName": "Joey",
		"familyName": "Anderson",
		"position": "RW",
		"shoots": "R",
		"height": 72,
		"weight": 207,
		"birthday": "1998-06-19",
		"birthplace": "Roseville, Minnesota, USA"
	},
	{
		"id": 2,
		"shirtNumber": 89,
		"givenName": "Andreas",
		"familyName": "Athanasiou",
		"position": "C",
		"shoots": "L",
		"height": 74,
		"weight": 190,
		"birthday": "1994-08-06",
		"birthplace": "Woodbridge, Ontario, CAN"
	},
	{
		"id": 3,
		"shirtNumber": 98,
		"givenName": "Connor",
		"familyName": "Bedard",
		"position": "C",
		"shoots": "R",
		"height": 70,
		"weight": 185,
		"birthday": "2005-07-17",
		"birthplace": "North Vancouver, British Columbia, CAN"
	},
	{
		"id": 4,
		"shirtNumber": 59,
		"givenName": "Tyler",
		"familyName": "Bertuzzi",
		"position": "LW",
		"shoots": "L",
		"height": 74,
		"weight": 299,
		"birthday": "1995-02-24",
		"birthplace": "Sudbury, Ontario CAN"
	},
	{
		"id": 5,
		"shirtNumber": 28,
		"givenName": "Colton",
		"familyName": "Dach",
		"position": "C",
		"shoots": "L",
		"height": 76,
		"weight": 185,
		"birthday": "2003-01-04",
		"birthplace": "St. Albert, Alberta, CAN"
	},
	{
		"id": 6,
		"shirtNumber": 16,
		"givenName": "Jason",
		"familyName": "Dickenson",
		"position": "C",
		"shoots": "L",
		"height": 74,
		"weight": 200,
		"birthday": "1995-07-04",
		"birthplace": "Georgetown, Ontario, CAN"
	},
	{
		"id": 7,
		"shirtNumber": 8,
		"givenName": "Ryan",
		"familyName": "Danato",
		"position": "C",
		"shoots": "L",
		"height": 72,
		"weight": 190,
		"birthday": "1996-04-09",
		"birthplace": "Boston, Massachusetts, USA"
	},
	{
		"id": 8,
		"shirtNumber": 17,
		"givenName": "Nick",
		"familyName": "Foligno",
		"position": "LW",
		"shoots": "L",
		"height": 72,
		"weight": 210,
		"birthday": "1987-10-31",
		"birthplace": "Buffalo, New York, USA"
	},
	{
		"id": 9,
		"shirtNumber": 70,
		"givenName": "Cole",
		"familyName": "Guttman",
		"position": "C",
		"shoots": "R",
		"height": 71,
		"weight": 167,
		"birthday": "1999-04-06",
		"birthplace": "Northridge, California, USA"
	},
	{
		"id": 10,
		"shirtNumber": 71,
		"givenName": "Taylor",
		"familyName": "Hall",
		"position": "LW",
		"shoots": "L",
		"height": 73,
		"weight": 210,
		"birthday": "1991-11-04",
		"birthplace": "Calgary, Alberta, CAN"
	},
	{
		"id": 11,
		"shirtNumber": 92,
		"givenName": "Gavin",
		"familyName": "Hayes",
		"position": "LW",
		"shoots": "R",
		"height": 73,
		"weight": 177,
		"birthday": "2004-05-14",
		"birthplace": "Ypsilanti, Michican, USA"
	},
	{
		"id": 12,
		"shirtNumber": 23,
		"givenName": "Phillipp",
		"familyName": "Kurashev",
		"position": "C",
		"shoots": "L",
		"height": 72,
		"weight": 190,
		"birthday": "1999-10-12",
		"birthplace": "Munsingen, CHE"
	},
	{
		"id": 13,
		"shirtNumber": 76,
		"givenName": "Nick",
		"familyName": "Lardis",
		"position": "LW",
		"shoots": "L",
		"height": 71,
		"weight": 165,
		"birthday": "2005-07-08",
		"birthplace": "Oakville, Ontario, CAN"
	},
	{
		"id": 14,
		"shirtNumber": 90,
		"givenName": "Paul",
		"familyName": "Ludwinski",
		"position": "C",
		"shoots": "L",
		"height": 71,
		"weight": 172,
		"birthday": "2004-04-23",
		"birthplace": "Toronto, Ontario, CAN"
	},
	{
		"id": 15,
		"shirtNumber": 43,
		"givenName": "Jalen",
		"familyName": "Luypen",
		"position": "C",
		"shoots": "L",
		"height": 70,
		"weight": 155,
		"birthday": "2002-06-28",
		"birthplace": "Lelowna, British Columbia, CAN"
	},
	{
		"id": 16,
		"shirtNumber": 77,
		"givenName": "Patrick",
		"familyName": "Maroon",
		"position": "LW",
		"shoots": "L",
		"height": 75,
		"weight": 234,
		"birthday": "1988-04-23",
		"birthplace": "St. Louis, Missouri, USA"
	},
	{
		"id": 17,
		"shirtNumber": 95,
		"givenName": "Ilya",
		"familyName": "Mikheyev",
		"position": "RW",
		"shoots": "L",
		"height": 74,
		"weight": 192,
		"birthday": "1994-10-10",
		"birthplace": "Omsk, RUS"
	},
	{
		"id": 18,
		"shirtNumber": 91,
		"givenName": "Frank",
		"familyName": "Nazar",
		"position": "LW",
		"shoots": "L",
		"height": 71,
		"weight": 175,
		"birthday": "2004-01-14",
		"birthplace": "Detroit, Michagan, USA"
	},
	{
		"id": 19,
		"shirtNumber": 73,
		"givenName": "Lukas",
		"familyName": "Reichel",
		"position": "LW",
		"shoots": "L",
		"height": 72,
		"weight": 170,
		"birthday": "2002-05-17",
		"birthplace": "Nurnberg, DEU"
	},
	{
		"id": 20,
		"shirtNumber": 36,
		"givenName": "Ryder",
		"familyName": "Rolston",
		"position": "RW",
		"shoots": "R",
		"height": 73,
		"weight": 175,
		"birthday": "2001-10-31",
		"birthplace": "Boston, Massachsetts, USA"
	},
	{
		"id": 21,
		"shirtNumber": 13,
		"givenName": "Zachary",
		"familyName": "Sanford",
		"position": "LW",
		"shoots": "L",
		"height": 76,
		"weight": 206,
		"birthday": "1994-11-09",
		"birthplace": "Salem, Massachusetts, USA"
	},
	{
		"id": 22,
		"shirtNumber": 67,
		"givenName": "Samuel",
		"familyName": "Savoie",
		"position": "LW",
		"shoots": "L",
		"height": 70,
		"weight": 189,
		"birthday": "2004-03-25",
		"birthplace": "Dieppe, New Brunswick, CAN"
	},
	{
		"id": 23,
		"shirtNumber": 62,
		"givenName": "Brett",
		"familyName": "Seney",
		"position": "LW",
		"shoots": "L",
		"height": 71,
		"weight": 156,
		"birthday": "1996-02-28",
		"birthplace": "London, Ontario, CAN"
	},
	{
		"id": 24,
		"shirtNumber": 84,
		"givenName": "Landon",
		"familyName": "Slaggert",
		"position": "LW",
		"shoots": "L",
		"height": 72,
		"weight": 180,
		"birthday": "2002-06-25",
		"birthplace": "South Bend, Indiana, USA"
	},
	{
		"id": 25,
		"shirtNumber": 15,
		"givenName": "Craig",
		"familyName": "Smith",
		"position": "C",
		"shoots": "R",
		"height": 73,
		"weight": 203,
		"birthday": "1989-08-05",
		"birthplace": "Madison, Wisconsin, USA"
	},
	{
		"id": 26,
		"shirtNumber": 86,
		"givenName": "Teuvo",
		"familyName": "Teravainen",
		"position": "C",
		"shoots": "L",
		"height": 73,
		"weight": 191,
		"birthday": "1994-09-11",
		"birthplace": "Helsinki, FIN"
	},
	{
		"id": 27,
		"shirtNumber": 0,
		"givenName": "Marek",
		"familyName": "Vanacker",
		"position": "LW",
		"shoots": "L",
		"height": 73,
		"weight": 174,
		"birthday": "2006-04-12",
		"birthplace": "London, Ontario, CAN"
	},
	{
		"id": 28,
		"shirtNumber": 42,
		"givenName": "Nolan",
		"familyName": "Alan",
		"position": "D",
		"shoots": "L",
		"height": 74,
		"weight": 195,
		"birthday": "2003-04-28",
		"birthplace": "Saskatoon, Saslatchewan, CAN"
	},
	{
		"id": 29,
		"shirtNumber": 78,
		"givenName": "TJ",
		"familyName": "Brodie",
		"position": "D",
		"shoots": "L",
		"height": 74,
		"weight": 187,
		"birthday": "1990-06-07",
		"birthplace": "Chatham, Ontario, CAN"
	},
	{
		"id": 30,
		"shirtNumber": 46,
		"givenName": "Louis",
		"familyName": "Crevier",
		"position": "D",
		"shoots": "R",
		"height": 80,
		"weight": 228,
		"birthday": "2001-05-01",
		"birthplace": "Quebec City, Quebec, CAN"
	},
	{
		"id": 31,
		"shirtNumber": 38,
		"givenName": "Ethan",
		"familyName": "Del Mastro",
		"position": "D",
		"shoots": "L",
		"height": 76,
		"weight": 210,
		"birthday": "2003-01-15",
		"birthplace": "Burlington, Ontario, CAN"
	},
	{
		"id": 32,
		"shirtNumber": 4,
		"givenName": "Seth",
		"familyName": "Jones",
		"position": "D",
		"shoots": "R",
		"height": 76,
		"weight": 213,
		"birthday": "1994-10-03",
		"birthplace": "Arlington, Texas, USA"
	},
	{
		"id": 33,
		"shirtNumber": 44,
		"givenName": "Wyatt",
		"familyName": "Kaiser",
		"position": "D",
		"shoots": "L",
		"height": 72,
		"weight": 173,
		"birthday": "2002-07-31",
		"birthplace": "Andover, Minnesota, USA"
	},
	{
		"id": 34,
		"shirtNumber": 14,
		"givenName": "Kevin",
		"familyName": "Korchinski",
		"position": "D",
		"shoots": "L",
		"height": 73,
		"weight": 185,
		"birthday": "2004-06-21",
		"birthplace": "Saskatoon, Saskatchewan, CAN"
	},
	{
		"id": 35,
		"shirtNumber": 55,
		"givenName": "Artyom",
		"familyName": "Levshunov",
		"position": "D",
		"shoots": "R",
		"height": 74,
		"weight": 208,
		"birthday": "2005-10-28",
		"birthplace": "Zhlobin, BLR"
	},
	{
		"id": 36,
		"shirtNumber": 25,
		"givenName": "Alec",
		"familyName": "Martinez",
		"position": "D",
		"shoots": "L",
		"height": 73,
		"weight": 210,
		"birthday": "1987-06-26",
		"birthplace": "Rochester Hills, Michigan, USA"
	},
	{
		"id": 37,
		"shirtNumber": 5,
		"givenName": "Connor",
		"familyName": "Murphy",
		"position": "D",
		"shoots": "R",
		"height": 76,
		"weight": 200,
		"birthday": "1993-03-26",
		"birthplace": "Dublin, Ohio, USA"
	},
	{
		"id": 38,
		"shirtNumber": 41,
		"givenName": "Isaak",
		"familyName": "Phillips",
		"position": "D",
		"shoots": "L",
		"height": 75,
		"weight": 205,
		"birthday": "2001-09-28",
		"birthplace": "Barrie, Ontario, CAN"
	},
	{
		"id": 39,
		"shirtNumber": 72,
		"givenName": "Alex",
		"familyName": "Vlasic",
		"position": "D",
		"shoots": "L",
		"height": 78,
		"weight": 217,
		"birthday": "2001-06-05",
		"birthplace": "Wilmette, illinois, USA"
	},
	{
		"id": 40,
		"shirtNumber": 39,
		"givenName": "Laurent",
		"familyName": "Brossoit",
		"position": "G",
		"shoots": "L",
		"height": 75,
		"weight": 203,
		"birthday": "1993-03-23",
		"birthplace": "Port Alberni, British Columbia, CAN"
	},
	{
		"id": 41,
		"shirtNumber": 29,
		"givenName": "Drew",
		"familyName": "Commesso",
		"position": "G",
		"shoots": "L",
		"height": 74,
		"weight": 180,
		"birthday": "2002-07-19",
		"birthplace": "Norwell, Massachusetts, USA"
	},
	{
		"id": 42,
		"shirtNumber": 34,
		"givenName": "Petr",
		"familyName": "Mrazek",
		"position": "G",
		"shoots": "L",
		"height": 74,
		"weight": 188,
		"birthday": "1992-02-14",
		"birthplace": "Ostrava, CZE"
	},
	{
		"id": 43,
		"shirtNumber": 40,
		"givenName": "Arvid",
		"familyName": "Soderblom",
		"position": "G",
		"shoots": "L",
		"height": 75,
		"weight": 180,
		"birthday": "1999-08-19",
		"birthplace": "Goteborg, SWE"
	}
]